py2_package_finder/__main__.py
py2_package_finder-1.0.0.dist-info/METADATA
py2_package_finder-1.0.0.dist-info/WHEEL
py2_package_finder-1.0.0.dist-info/entry_points.txt
py2_package_finder-1.0.0.dist-info/RECORD
